[
    {
        "key": "dbln",
        "value": "%7B%22100094700234726%22%3A%22WBf0dm1V%22%7D",
        "domain": "facebook.com",
        "path": "/login/device-based/",
        "hostOnly": false,
        "creation": "2025-06-09T13:35:58.313Z",
        "lastAccessed": "2025-06-09T13:35:58.313Z"
    },
    {
        "key": "sb",
        "value": "U5P_ZT0lhGXu8G8lK6hTi0eT",
        "domain": "facebook.com",
        "path": "/",
        "hostOnly": false,
        "creation": "2025-06-09T13:35:58.313Z",
        "lastAccessed": "2025-06-09T13:35:58.313Z"
    },
    {
        "key": "ps_n",
        "value": "1",
        "domain": "facebook.com",
        "path": "/",
        "hostOnly": false,
        "creation": "2025-06-09T13:35:58.313Z",
        "lastAccessed": "2025-06-09T13:35:58.313Z"
    },
    {
        "key": "ps_l",
        "value": "1",
        "domain": "facebook.com",
        "path": "/",
        "hostOnly": false,
        "creation": "2025-06-09T13:35:58.313Z",
        "lastAccessed": "2025-06-09T13:35:58.313Z"
    },
    {
        "key": "wl_cbv",
        "value": "v2%3Bclient_version%3A2764%3Btimestamp%3A1742094399",
        "domain": "facebook.com",
        "path": "/",
        "hostOnly": false,
        "creation": "2025-06-09T13:35:58.313Z",
        "lastAccessed": "2025-06-09T13:35:58.313Z"
    },
    {
        "key": "dpr",
        "value": "3.632967948913574",
        "domain": "facebook.com",
        "path": "/",
        "hostOnly": false,
        "creation": "2025-06-09T13:35:58.313Z",
        "lastAccessed": "2025-06-09T13:35:58.313Z"
    },
    {
        "key": "locale",
        "value": "ar_AR",
        "domain": "facebook.com",
        "path": "/",
        "hostOnly": false,
        "creation": "2025-06-09T13:35:58.313Z",
        "lastAccessed": "2025-06-09T13:35:58.313Z"
    },
    {
        "key": "datr",
        "value": "c9RGaJd8bvrPkBkCtJuKzDdm",
        "domain": "facebook.com",
        "path": "/",
        "hostOnly": false,
        "creation": "2025-06-09T13:35:58.313Z",
        "lastAccessed": "2025-06-09T13:35:58.313Z"
    },
    {
        "key": "wd",
        "value": "809x1495",
        "domain": "facebook.com",
        "path": "/",
        "hostOnly": false,
        "creation": "2025-06-09T13:35:58.313Z",
        "lastAccessed": "2025-06-09T13:35:58.313Z"
    },
    {
        "key": "c_user",
        "value": "100094700234726",
        "domain": "facebook.com",
        "path": "/",
        "hostOnly": false,
        "creation": "2025-06-09T13:35:58.313Z",
        "lastAccessed": "2025-06-09T13:35:58.313Z"
    },
    {
        "key": "xs",
        "value": "43%3ADsLU9sQMnDGd8g%3A2%3A1749472595%3A-1%3A-1",
        "domain": "facebook.com",
        "path": "/",
        "hostOnly": false,
        "creation": "2025-06-09T13:35:58.313Z",
        "lastAccessed": "2025-06-09T13:35:58.313Z"
    },
    {
        "key": "fr",
        "value": "1mcScZnKP3WCZHIuq.AWcfyiP2oAH-2zfxuOO6gkJp6zvvMLgIoiREfXUELwLG17VVRAQ.BoRs07..AAA.0.0.BoRuMv.AWdUfpRbGMZFSLJlYBJFqqnMy1U",
        "domain": "facebook.com",
        "path": "/",
        "hostOnly": false,
        "creation": "2025-06-09T13:35:58.313Z",
        "lastAccessed": "2025-06-09T13:35:58.313Z"
    },
    {
        "key": "presence",
        "value": "C%7B%22t3%22%3A%5B%5D%2C%22utc3%22%3A1749476151237%2C%22v%22%3A1%7D",
        "domain": "facebook.com",
        "path": "/",
        "hostOnly": false,
        "creation": "2025-06-09T13:35:58.313Z",
        "lastAccessed": "2025-06-09T13:35:58.313Z"
    }
]
